MANIFEST.in
README.rst
TITLE.txt
lh-agpl3-LICENSE.txt
setup.py
./bin/seedIcmStandalone.bash
bisos2/__init__.py
bisos2.bashStandaloneIcmSeed.egg-info/PKG-INFO
bisos2.bashStandaloneIcmSeed.egg-info/SOURCES.txt
bisos2.bashStandaloneIcmSeed.egg-info/dependency_links.txt
bisos2.bashStandaloneIcmSeed.egg-info/namespace_packages.txt
bisos2.bashStandaloneIcmSeed.egg-info/not-zip-safe
bisos2.bashStandaloneIcmSeed.egg-info/top_level.txt
bisos2/bashStandaloneIcmSeed/__init__.py
bisos2/bashStandaloneIcmSeed/bashStandaloneIcmSeedPkgThis.py